nao_context_manager.py
nao_context_manager-1.0.1.dist-info/METADATA
nao_context_manager-1.0.1.dist-info/WHEEL
nao_context_manager-1.0.1.dist-info/top_level.txt
nao_context_manager-1.0.1.dist-info/RECORD
