Metadata-Version: 2.2
Name: nao_context_manager
Version: 1.0.1
Summary: A context manager for nao's use.
Project-URL: Homepage, https://github.com/XMENTROPY/nao_context_manager
